{
    "familia": [{
            "parentezco": "xxxxx",
            "Nombres": "xxxxx",
            "Apellidos": "xxxxxxxx",
            "edad": 14
        },
        {
            "parentezco": "xxxxx",
            "Nombres": "xxxxx",
            "Apellidos": "xxxxxxxx",
            "edad": 14
        },
        {
            "parentezco": "xxxxx",
            "Nombres": "xxxxx",
            "Apellidos": "xxxxxxxx",
            "edad": 14
        },
        {
            "parentezco": "xxxxx",
            "Nombres": "xxxxx",
            "Apellidos": "xxxxxxxx",
            "edad": 14
        },
        {
            "parentezco": "xxxxx",
            "Nombres": "xxxxx",
            "Apellidos": "xxxxxxxx",
            "edad": 14
        },
        {
            "parentezco": "xxxxx",
            "Nombres": "xxxxx",
            "Apellidos": "xxxxxxxx",
            "edad": 14
        }


    ]
}